scorebook/__init__.py
scorebook/cli/__init__.py
scorebook/cli/auth.py
scorebook/cli/main.py
scorebook/eval_datasets/__init__.py
scorebook/eval_datasets/eval_dataset.py
scorebook/evaluate/__init__.py
scorebook/evaluate/_async/__init__.py
scorebook/evaluate/_async/evaluate_async.py
scorebook/evaluate/_sync/__init__.py
scorebook/evaluate/_sync/evaluate.py
scorebook/evaluate/evaluate_helpers.py
scorebook/exceptions.py
scorebook/inference/__init__.py
scorebook/inference/clients/__init__.py
scorebook/inference/clients/bedrock.py
scorebook/inference/clients/openai.py
scorebook/inference/clients/portkey.py
scorebook/inference/clients/vertex.py
scorebook/inference/inference_pipeline.py
scorebook/metrics/__init__.py
scorebook/metrics/accuracy.py
scorebook/metrics/metric_base.py
scorebook/metrics/metric_registry.py
scorebook/metrics/precision.py
scorebook/score/__init__.py
scorebook/score/_async/__init__.py
scorebook/score/_async/score_async.py
scorebook/score/_sync/__init__.py
scorebook/score/_sync/score.py
scorebook/score/score_helpers.py
scorebook/settings.py
scorebook/trismik/__init__.py
scorebook/trismik/credentials.py
scorebook/trismik/upload_results.py
scorebook/types.py
scorebook/utils/__init__.py
scorebook/utils/async_utils.py
scorebook/utils/common_helpers.py
scorebook/utils/io_helpers.py
scorebook/utils/jinja_helpers.py
scorebook/utils/mappers.py
scorebook/utils/progress_bars.py
scorebook/utils/render_template.py
scorebook/utils/transform_helpers.py
scorebook-0.0.13.dist-info/METADATA
scorebook-0.0.13.dist-info/WHEEL
scorebook-0.0.13.dist-info/entry_points.txt
scorebook-0.0.13.dist-info/licenses/LICENSE
scorebook-0.0.13.dist-info/RECORD
