Metadata-Version: 2.4
Name: scorebook
Version: 0.0.13
Summary: A Python project for LLM evaluation.
License-File: LICENSE
Author: Euan Campbell
Author-email: euan@trismik.com
Requires-Python: >=3.9, <3.14
Classifier: Programming Language :: Python :: 3
Classifier: Programming Language :: Python :: 3.9
Classifier: Programming Language :: Python :: 3.10
Classifier: Programming Language :: Python :: 3.11
Classifier: Programming Language :: Python :: 3.12
Classifier: Programming Language :: Python :: 3.13
Provides-Extra: bedrock
Provides-Extra: examples
Provides-Extra: openai
Provides-Extra: portkey
Provides-Extra: vertex
Requires-Dist: accelerate ; extra == "examples"
Requires-Dist: boto3 (==1.40.0) ; extra == "bedrock"
Requires-Dist: datasets (>=3.6.0)
Requires-Dist: fsspec[gcs] ; extra == "vertex"
Requires-Dist: google-cloud-storage ; extra == "vertex"
Requires-Dist: google-genai ; extra == "vertex"
Requires-Dist: ipywidgets (>=8.0.0)
Requires-Dist: notebook (>=7.4.5,<8.0.0)
Requires-Dist: notebook ; extra == "examples"
Requires-Dist: openai ; extra == "openai"
Requires-Dist: pandas ; extra == "vertex"
Requires-Dist: portkey-ai ; extra == "portkey"
Requires-Dist: python-dotenv ; extra == "bedrock"
Requires-Dist: python-dotenv ; extra == "openai"
Requires-Dist: python-dotenv ; extra == "portkey"
Requires-Dist: python-dotenv ; extra == "vertex"
Requires-Dist: torch ; extra == "examples"
Requires-Dist: torchaudio ; extra == "examples"
Requires-Dist: torchvision ; extra == "examples"
Requires-Dist: transformers ; extra == "examples"
Requires-Dist: trismik (==1.0.2)
